ffdl/__init__.py
ffdl/client/Config.py
ffdl/client/FfDLClient.py
ffdl/client/__init__.py
ffdl_client-0.1.2.dist-info/LICENSE
ffdl_client-0.1.2.dist-info/METADATA
ffdl_client-0.1.2.dist-info/WHEEL
ffdl_client-0.1.2.dist-info/top_level.txt
ffdl_client-0.1.2.dist-info/RECORD
